koreanbots/__init__.py
koreanbots/client.py
koreanbots/decorator.py
koreanbots/errors.py
koreanbots/http.py
koreanbots/model.py
koreanbots/py.typed
koreanbots/typing.py
koreanbots/integrations/__init__.py
koreanbots/integrations/dico.py
koreanbots/integrations/discord.py
koreanbots-3.1.0.dist-info/licenses/LICENSE
koreanbots-3.1.0.dist-info/METADATA
koreanbots-3.1.0.dist-info/WHEEL
koreanbots-3.1.0.dist-info/top_level.txt
koreanbots-3.1.0.dist-info/RECORD
