Metadata-Version: 2.4
Name: koreanbots
Version: 3.1.0
Summary: Official SDK for Koreanbots.
Home-page: https://github.com/koreanbots/py-sdk
Author: Koreanbots
License: MIT
Project-URL: Homepage, https://koreanbots.dev/
Project-URL: Source, https://github.com/koreanbots/py-sdk
Project-URL: Tracker, https://github.com/koreanbots/py-sdk/issues
Classifier: Programming Language :: Python :: 3.8
Classifier: Programming Language :: Python :: 3.9
Requires-Python: >=3.8
License-File: LICENSE
Requires-Dist: aiohttp
Dynamic: author
Dynamic: classifier
Dynamic: description
Dynamic: description-content-type
Dynamic: home-page
Dynamic: license
Dynamic: license-file
Dynamic: project-url
Dynamic: requires-dist
Dynamic: requires-python
Dynamic: summary
